{
  "id": "",
  "name": "",
  "font_family": "iconfont",
  "css_prefix_text": "icon-",
  "description": "",
  "glyphs": [
    {
      "icon_id": "14846193",
      "name": "龟背竹",
      "font_class": "2",
      "unicode": "e623",
      "unicode_decimal": 58915
    },
    {
      "icon_id": "14846262",
      "name": "绿植1",
      "font_class": "lvzhi1",
      "unicode": "e624",
      "unicode_decimal": 58916
    },
    {
      "icon_id": "14871017",
      "name": "绿植3",
      "font_class": "lvzhi3",
      "unicode": "e629",
      "unicode_decimal": 58921
    },
    {
      "icon_id": "14871018",
      "name": "绿植4",
      "font_class": "lvzhi4",
      "unicode": "e62a",
      "unicode_decimal": 58922
    },
    {
      "icon_id": "14871019",
      "name": "绿植8",
      "font_class": "lvzhi8",
      "unicode": "e62b",
      "unicode_decimal": 58923
    }
  ]
}
